{"title":"git clone <repo> --depth 1","permalink":"/posts/git-clone-depth","post":{"title":"git clone <repo> --depth 1","language":"zh-tw","date":"2016-06-16T00:00:00.000Z","categories":"Diary","__content":"<p>Just find out a way to speed up the build of docker image for testing environment. We can use <code>git clone &lt;repo&gt; --depth 1</code> to get the repo with latest copy only. In other words, no commit history is cloned.</p>\n<p>It can speed up the <code>git clone</code>, especially your project is big and with long history.</p>","filePath":"/Users/sunday/workspace/coding-sunday/source/_posts/diary/git-clone-depth.md","slug":"git-clone-depth"}}